{
  "id": "level1",
  "name": "The Dungeons",
  "timeLimit": 90,
  "tiles": [
    "##############################",
    "#............................#",
    "#...T.......T.......T.....T..#",
    "#............................#",
    "#....===........===..........#",
    "#S..........................E#",
    "#######LL##..##^^#####..######",
    "#######..##..#########..######"
  ],
  "spawn": {
    "x": 1,
    "y": 5
  },
  "entities": [
    {
      "type": "guard",
      "x": 24,
      "y": 5,
      "hp": 3,
      "patrol": [
        20,
        28
      ]
    }
  ],
  "potions": [
    {
      "x": 17,
      "y": 5,
      "effect": "heal"
    }
  ],
  "objects": [],
  "secrets": []
}
